pythonp/__init__.py
pythonp/__main__.py
pythonp-0.3.6.dist-info/METADATA
pythonp-0.3.6.dist-info/RECORD
pythonp-0.3.6.dist-info/WHEEL
pythonp-0.3.6.dist-info/entry_points.txt
pythonp-0.3.6.dist-info/top_level.txt
