Metadata-Version: 2.1
Name: pythonp
Version: 0.3.6
Summary: A powerful utility that empowers pythonistas in the command line
Home-page: https://github.com/bombs-kim/pythonp
Author: Beomsoo Kim
Author-email: bluewhale8202@gmail.com
License: UNKNOWN
Platform: UNKNOWN
Classifier: Programming Language :: Python :: 2
Classifier: Programming Language :: Python :: 3
Classifier: License :: OSI Approved :: MIT License
Classifier: Operating System :: OS Independent
